templaterSPLN/__init__.py
templaterSPLN/templates/template.txt
templaterSPLN/templates/templateMaven.txt
templaterspln-0.2.dist-info/entry_points.txt
templaterspln-0.2.dist-info/LICENSE
templaterspln-0.2.dist-info/WHEEL
templaterspln-0.2.dist-info/METADATA
templaterspln-0.2.dist-info/RECORD
