Metadata-Version: 2.1
Name: templaterSPLN
Version: 0.2
Summary: Simple program that reads a template file and creates the folder structure and files based on the template.
Author-email: JC <pg50469@alunos.uminho.pt>, HB <pg50418@alunos.uminho.pt>, DF <pg50306@alunos.uminho.pt>
Classifier: License :: OSI Approved :: MIT License
Requires-Dist: argparse
